{"name":"build-javascript","namedChunkGroups":{"polyfill":{"name":"polyfill","assets":[{"name":"webpack-runtime-70a90b91821a7b6d4a28.js","size":4705},{"name":"polyfill-4718f0fec20e0d09d7f5.js","size":85862}],"filteredAssets":0,"assetsSize":90567,"filteredAuxiliaryAssets":2,"auxiliaryAssetsSize":226259},"app":{"name":"app","assets":[{"name":"webpack-runtime-70a90b91821a7b6d4a28.js","size":4705},{"name":"styles.7981faae0f7f8b56bb12.css","size":12456},{"name":"framework-47730820c6d935055723.js","size":129775},{"name":"app-c923b711143f109248b4.js","size":57336}],"filteredAssets":0,"assetsSize":204272,"filteredAuxiliaryAssets":3,"auxiliaryAssetsSize":572471},"component---src-pages-404-tsx":{"name":"component---src-pages-404-tsx","assets":[{"name":"styles.7981faae0f7f8b56bb12.css","size":12456},{"name":"777cf710-f9a5400e79e8e96eaf92.js","size":77939},{"name":"commons-bb95c37ba50e0c3d8251.js","size":87926},{"name":"component---src-pages-404-tsx-9424d9cc1b925866b7a4.js","size":4972}],"filteredAssets":0,"assetsSize":183293,"filteredAuxiliaryAssets":3,"auxiliaryAssetsSize":731136},"component---src-pages-index-tsx":{"name":"component---src-pages-index-tsx","assets":[{"name":"styles.7981faae0f7f8b56bb12.css","size":12456},{"name":"777cf710-f9a5400e79e8e96eaf92.js","size":77939},{"name":"commons-bb95c37ba50e0c3d8251.js","size":87926},{"name":"c8834c975d90390e8e70f5b303c381640afbb8e1-9c62fff0eed3fb60dcb5.js","size":11807},{"name":"component---src-pages-index-tsx-a6154c178465b2c0864f.js","size":6857}],"filteredAssets":0,"assetsSize":196985,"filteredAuxiliaryAssets":4,"auxiliaryAssetsSize":782044},"component---src-pages-projects-tsx":{"name":"component---src-pages-projects-tsx","assets":[{"name":"styles.7981faae0f7f8b56bb12.css","size":12456},{"name":"framework-47730820c6d935055723.js","size":129775},{"name":"777cf710-f9a5400e79e8e96eaf92.js","size":77939},{"name":"commons-bb95c37ba50e0c3d8251.js","size":87926},{"name":"c8834c975d90390e8e70f5b303c381640afbb8e1-9c62fff0eed3fb60dcb5.js","size":11807},{"name":"component---src-pages-projects-tsx-3b8c82f282fb4a453782.js","size":32991}],"filteredAssets":0,"assetsSize":352894,"filteredAuxiliaryAssets":5,"auxiliaryAssetsSize":1211470},"component---src-pages-timeline-tsx":{"name":"component---src-pages-timeline-tsx","assets":[{"name":"styles.7981faae0f7f8b56bb12.css","size":12456},{"name":"777cf710-f9a5400e79e8e96eaf92.js","size":77939},{"name":"commons-bb95c37ba50e0c3d8251.js","size":87926},{"name":"component---src-pages-timeline-tsx-394fcd8d00de54a76d94.js","size":6450}],"filteredAssets":0,"assetsSize":184771,"filteredAuxiliaryAssets":3,"auxiliaryAssetsSize":731916}},"assetsByChunkName":{"polyfill":["webpack-runtime-70a90b91821a7b6d4a28.js","polyfill-4718f0fec20e0d09d7f5.js"],"app":["webpack-runtime-70a90b91821a7b6d4a28.js","styles.7981faae0f7f8b56bb12.css","framework-47730820c6d935055723.js","app-c923b711143f109248b4.js"],"component---src-pages-404-tsx":["styles.7981faae0f7f8b56bb12.css","777cf710-f9a5400e79e8e96eaf92.js","commons-bb95c37ba50e0c3d8251.js","component---src-pages-404-tsx-9424d9cc1b925866b7a4.js"],"component---src-pages-index-tsx":["styles.7981faae0f7f8b56bb12.css","777cf710-f9a5400e79e8e96eaf92.js","commons-bb95c37ba50e0c3d8251.js","c8834c975d90390e8e70f5b303c381640afbb8e1-9c62fff0eed3fb60dcb5.js","component---src-pages-index-tsx-a6154c178465b2c0864f.js"],"component---src-pages-projects-tsx":["styles.7981faae0f7f8b56bb12.css","framework-47730820c6d935055723.js","777cf710-f9a5400e79e8e96eaf92.js","commons-bb95c37ba50e0c3d8251.js","c8834c975d90390e8e70f5b303c381640afbb8e1-9c62fff0eed3fb60dcb5.js","component---src-pages-projects-tsx-3b8c82f282fb4a453782.js"],"component---src-pages-timeline-tsx":["styles.7981faae0f7f8b56bb12.css","777cf710-f9a5400e79e8e96eaf92.js","commons-bb95c37ba50e0c3d8251.js","component---src-pages-timeline-tsx-394fcd8d00de54a76d94.js"]},"childAssetsByChunkName":{}}